Lab1-half-full-adder/half_adder.vhdl
library ieee;
use ieee.std_logic_1164.all;

entity half_adder is
    port (
        i, ii : in std_logic;
        sum, carry : out std_logic
    );
end half_adder;

architecture arch of half_adder is
begin
    sum <= i xor ii;
    carry <= i and ii;
end arch;

Lab1-half-full-adder/full_adder.vhdl
-- one bit full adder

library ieee;
use ieee.std_logic_1164.all;

entity full_adder is
    port (
        a, b, ci : in std_logic;
        s, c : out std_logic
    );
end full_adder;


architecture arch of full_adder is
    component half_adder
        port (
            i, ii : in std_logic;
            sum, carry : out std_logic
        );
    end component;

    for half_adder_0: half_adder use entity work.half_adder;
    for half_adder_1: half_adder use entity work.half_adder;
    signal asb, aab, asbco: std_logic;

    -- Instantiation
begin
    half_adder_0: half_adder port map(
        -- entity-signal-name => local-signal-name
        i => a,
        ii => b,
        sum => asb,
        carry => aab
    );
    half_adder_1: half_adder port map(
        i => asb,
        ii => ci,
        sum => s,
        carry => asbco
    );

    c <= aab or asbco;
end arch;

Lab1-half-full-adder/cun_test_bench.vhdl
library ieee;
use ieee.std_logic_1164.all;


entity full_adder_tb is
end full_adder_tb;

architecture tb of full_adder_tb is
    signal a, b, ci : std_logic;  -- inputs
    signal sum, carry : std_logic;  -- outputs
begin
    -- connecting testbench signals with full_adder.vhdl
    UUT : entity work.full_adder port map (a => a, b => b, ci => ci, s => sum, c => carry);

    -- inputs
    -- ci ba
    --  0 00 at   0 ns
    --  0 01 at  20 ns
    --  0 10 at  40 ns
    --  0 11 at  60 ns
    --  1 00 at  80 ns
    --  1 01 at 100 ns
    --  1 10 at 120 ns
    --  1 11 at 140 ns
    --  1 11 at 160 ns

    a <= '0', '1' after 20 ns, '0' after 40 ns, '1' after 60 ns, '0' after 80 ns, '1' after 100 ns, '0' after 120 ns, '1' after 140 ns, '1' after 160 ns;
    b <= '0', '1' after 40 ns, '0' after 80 ns, '0' after 120 ns, '1' after 140 ns, '1' after 160 ns;
    ci <= '0', '1' after 80 ns, '1' after 120 ns, '1' after 160 ns;
end tb ;

Lab1-half-full-adder/ctb.vcd
$date
  Wed Oct 25 13:44:54 2023
$end
$version
  GHDL v0
$end
$timescale
  1 fs
$end
$scope module standard $end
$upscope $end
$scope module std_logic_1164 $end
$upscope $end
$scope module full_adder_tb $end
$var reg 1 ! a $end
$var reg 1 " b $end
$var reg 1 # ci $end
$var reg 1 $ sum $end
$var reg 1 % carry $end
$scope module uut $end
$var reg 1 & a $end
$var reg 1 ' b $end
$var reg 1 ( ci $end
$var reg 1 ) s $end
$var reg 1 * c $end
$var reg 1 + asb $end
$var reg 1 , aab $end
$var reg 1 - asbco $end
$scope module half_adder_0 $end
$var reg 1 . i $end
$var reg 1 / ii $end
$var reg 1 0 sum $end
$var reg 1 1 carry $end
$upscope $end
$scope module half_adder_1 $end
$var reg 1 2 i $end
$var reg 1 3 ii $end
$var reg 1 4 sum $end
$var reg 1 5 carry $end
$upscope $end
$upscope $end
$upscope $end
$enddefinitions $end
#0
0!
0"
0#
0$
0%
0&
0'
0(
0)
0*
0+
0,
0-
0.
0/
00
01
02
03
04
05
#20000000
1!
1$
1&
1)
1+
1.
10
12
14
#40000000
0!
1"
0&
1'
0.
1/
#60000000
1!
0$
1%
1&
0)
1*
0+
1,
1.
00
11
02
04
#80000000
0!
0"
1#
1$
0%
0&
0'
1(
1)
0*
0,
0.
0/
01
13
14
#100000000
1!
0$
1%
1&
0)
1*
1+
1-
1.
10
12
04
15
#120000000
0!
1$
0%
0&
1)
0*
0+
0-
0.
00
02
14
05
#140000000
1!
1"
1%
1&
1'
1*
1,
1.
1/
11
